<?xml version="1.0"?>
<!DOCTYPE service-builder PUBLIC "-//Liferay//DTD Service Builder 7.0.0//EN" "http://www.liferay.com/dtd/liferay-service-builder_7_0_0.dtd">

<service-builder package-path="org.opencps.statistic">
	<author>khoavu</author>
	<namespace>statistic</namespace>
	<entity local-service="true" name="OpencpsDossierStatistic"
		remote-service="false" table="opencps_statistic" uuid="true">

		<column name="dossierStatisticId" type="long" primary="true" />

		<!-- Audit fields -->
		<column name="companyId" type="long" />
		<column name="groupId" type="long" />
		<column name="userId" type="long" />
		<column name="userName" type="String" />
		<column name="createDate" type="Date" />
		<column name="modifiedDate" type="Date" />

		<column name="month" type="int" />
		<column name="year" type="int" />
		<column name="totalCount" type="int" />
		<column name="deniedCount" type="int" />
		<column name="cancelledCount" type="int" />
		<column name="processCount" type="int" />
		<column name="remainingCount" type="int" />
		<column name="receivedCount" type="int" />
		<column name="onlineCount" type="int" />
		<column name="onegateCount" type="int" />
		<column name="releaseCount" type="int" />
		<column name="betimesCount" type="int" />
		<column name="ontimeCount" type="int" />
		<column name="overtimeCount" type="int" />
		<column name="doneCount" type="int" />
		<column name="releasingCount" type="int" />
		<column name="unresolvedCount" type="int" />
		<column name="processingCount" type="int" />
		<column name="undueCount" type="int" />
		<column name="overdueCount" type="int" />
		<column name="pausingCount" type="int" />
		<column name="ontimePercentage" type="int" />
		<column name="govAgencyCode" type="String" />
		<column name="groupAgencyCode" type="String" />
		<column name="govAgencyName" type="String" />
		<column name="domainCode" type="String" />
		<column name="domainName" type="String" />
		<column name="reporting" type="boolean" />
		<column name="overtimeInside" type="int"/>
		<column name="overtimeOutside" type="int"/>
		<column name="interoperatingCount" type="int"/>
		<column name="waitingCount" type="int"/>
		
		<column name="outsideCount" type="int"/>
		<column name="insideCount" type="int"/>
		
		<!-- Order -->

		<!-- Filter -->
		<finder return-type="Collection" name="G_UID_Y">
			<finder-column name="groupId"></finder-column>
			<finder-column name="userId"></finder-column>
			<finder-column name="year"></finder-column>
		</finder>
		
		<finder return-type="OpencpsDossierStatistic" name="M_Y_DM_G">
			<finder-column name="groupId"/>
			<finder-column name="govAgencyCode"/>
			<finder-column name="month"/>
			<finder-column name="year"/>
			<finder-column name="domainCode"/>
			<finder-column name="reporting"/>
		</finder>
		
		<finder return-type="OpencpsDossierStatistic" name="G_M_Y_G_D">
			<finder-column name="groupId"/>
			<finder-column name="month"/>
			<finder-column name="year"/>
			<finder-column name="govAgencyCode"/>
			<finder-column name="domainCode"/>
		</finder>
		
		<finder return-type="OpencpsDossierStatistic" name="M_Y_G">
			<finder-column name="groupId"/>
			<finder-column name="govAgencyCode"/>
			<finder-column name="month"/>
			<finder-column name="year"/>
		</finder>

		<finder return-type="Collection" name="G_D_M_Y">
			<finder-column name="groupId"/>
			<finder-column name="domainCode"/>
			<finder-column name="month"/>
			<finder-column name="year"/>			
		</finder>

		<finder return-type="Collection" name="G_M_Y">
			<finder-column name="groupId"/>
			<finder-column name="month"/>
			<finder-column name="year"/>
		</finder>

		<finder return-type="Collection" name="CID_GID_Y">
			<finder-column name="companyId"/>
			<finder-column name="groupId"/>
			<finder-column name="month"/>
			<finder-column name="year"/>
		</finder>
		<finder return-type="Collection" name="GID_M_Y_RP">
			<finder-column name="groupId"/>
			<finder-column name="month"/>
			<finder-column name="year"/>
			<finder-column name="reporting"/>
		</finder>
		<finder return-type="Collection" name="GID_MS_Y_RP">
			<finder-column name="groupId"/>
			<finder-column name="month" comparator="=" arrayable-operator="OR"/>
			<finder-column name="year"/>
			<finder-column name="reporting"/>
		</finder>
		<finder return-type="Collection" name="G">
			<finder-column name="groupId"></finder-column>
		</finder>		
	</entity>

	<entity local-service="true" name="OpencpsVotingStatistic"
		remote-service="false" table="opencps_voting_statistic" uuid="true">

		<column name="votingStatisticId" type="long" primary="true" />

		<!-- Audit fields -->
		<column name="companyId" type="long" />
		<column name="groupId" type="long" />
		<column name="userId" type="long" />
		<column name="userName" type="String" />
		<column name="createDate" type="Date" />
		<column name="modifiedDate" type="Date" />

		<column name="month" type="int" />
		<column name="year" type="int" />
		<column name="govAgencyCode" type="String" />
		<column name="govAgencyName" type="String" />
		<column name="domainCode" type="String" />
		<column name="domainName" type="String" />
		<column name="votingCode" type="String" />
		<column name="votingSubject" type="String" />
		<column name="totalVoted" type="int" />
		<column name="veryGoodCount" type="int" />
		<column name="goodCount" type="int" />
		<column name="badCount" type="int" />
		<column name="percentVeryGood" type="int" />
		<column name="percentGood" type="int" />
		<column name="percentBad" type="int" />
		<column name="totalCount" type="int" />
		
		<!-- Filter -->
		<finder return-type="Collection" name="G_UID_Y">
			<finder-column name="groupId"></finder-column>
			<finder-column name="userId"></finder-column>
			<finder-column name="year"></finder-column>
		</finder>
		
		<finder return-type="OpencpsVotingStatistic" name="M_Y_DM_G">
			<finder-column name="groupId"/>
			<finder-column name="month"/>
			<finder-column name="year"/>
			<finder-column name="govAgencyCode"/>
			<finder-column name="domainCode"/>
		</finder>
		
		<finder return-type="Collection" name="G_D_M_Y">
			<finder-column name="groupId"/>
			<finder-column name="domainCode"/>
			<finder-column name="month"/>
			<finder-column name="year"/>
		</finder>

		<finder return-type="Collection" name="G_M_Y">
			<finder-column name="groupId"/>
			<finder-column name="month"/>
			<finder-column name="year"/>
		</finder>

		<finder return-type="Collection" name="CID_GID_Y">
			<finder-column name="companyId"/>
			<finder-column name="groupId"/>
			<finder-column name="month"/>
			<finder-column name="year"/>
		</finder>
	</entity>

	<entity local-service="true" name="OpencpsPersonStatistic"
		remote-service="false" table="opencps_person_statistic" uuid="true">

		<column name="personStatisticId" type="long" primary="true" />

		<!-- Audit fields -->
		<column name="companyId" type="long" />
		<column name="groupId" type="long" />
		<column name="userId" type="long" />
		<column name="userName" type="String" />
		<column name="createDate" type="Date" />
		<column name="modifiedDate" type="Date" />

		<column name="month" type="int" />
		<column name="year" type="int" />
		<column name="govAgencyCode" type="String" />
		<column name="govAgencyName" type="String" />
		<column name="employeeId" type="long" />
<!-- 		<column name="domainName" type="String" /> -->
		<column name="votingCode" type="String" />
		<column name="votingSubject" type="String" />
		<column name="totalVoted" type="int" />
		<column name="veryGoodCount" type="int" />
		<column name="goodCount" type="int" />
		<column name="badCount" type="int" />
		<column name="percentVeryGood" type="int" />
		<column name="percentGood" type="int" />
		<column name="percentBad" type="int" />
		<column name="totalCount" type="int" />

		<!-- Filter -->
		<finder return-type="Collection" name="G_UID_Y">
			<finder-column name="groupId"></finder-column>
			<finder-column name="userId"></finder-column>
			<finder-column name="year"></finder-column>
		</finder>

		<finder return-type="OpencpsVotingStatistic" name="M_Y_GOV_EMP">
			<finder-column name="groupId"/>
			<finder-column name="month"/>
			<finder-column name="year"/>
			<finder-column name="govAgencyCode"/>
			<finder-column name="employeeId"/>
		</finder>

		<finder return-type="Collection" name="G_D_M_Y">
			<finder-column name="groupId"/>
			<finder-column name="employeeId"/>
			<finder-column name="month"/>
			<finder-column name="year"/>
		</finder>

		<finder return-type="Collection" name="G_M_Y">
			<finder-column name="groupId"/>
			<finder-column name="month"/>
			<finder-column name="year"/>
		</finder>

		<finder return-type="Collection" name="CID_GID_Y">
			<finder-column name="companyId"/>
			<finder-column name="groupId"/>
			<finder-column name="month"/>
			<finder-column name="year"/>
		</finder>
	</entity>

</service-builder>